anki_audio/__init__.py
anki_audio/lame
anki_audio/mpv
anki_audio/libs/libSDL2-2.0.0.dylib
anki_audio/libs/libXau.6.dylib
anki_audio/libs/libXdmcp.6.dylib
anki_audio/libs/libaom.3.2.0.dylib
anki_audio/libs/libarchive.13.dylib
anki_audio/libs/libass.9.dylib
anki_audio/libs/libavcodec.58.134.100.dylib
anki_audio/libs/libavdevice.58.13.100.dylib
anki_audio/libs/libavfilter.7.110.100.dylib
anki_audio/libs/libavformat.58.76.100.dylib
anki_audio/libs/libavresample.4.0.0.dylib
anki_audio/libs/libavutil.56.70.100.dylib
anki_audio/libs/libb2.1.dylib
anki_audio/libs/libbluray.2.dylib
anki_audio/libs/libbrotlicommon.1.0.9.dylib
anki_audio/libs/libbrotlidec.1.0.9.dylib
anki_audio/libs/libbrotlienc.1.0.9.dylib
anki_audio/libs/libcjson.1.7.15.dylib
anki_audio/libs/libcrypto.1.1.dylib
anki_audio/libs/libdav1d.5.dylib
anki_audio/libs/libffi.8.dylib
anki_audio/libs/libfontconfig.1.dylib
anki_audio/libs/libfreetype.6.dylib
anki_audio/libs/libfribidi.0.dylib
anki_audio/libs/libgif.7.2.0.dylib
anki_audio/libs/libglib-2.0.0.dylib
anki_audio/libs/libgmp.10.dylib
anki_audio/libs/libgnutls.30.dylib
anki_audio/libs/libgraphite2.3.2.1.dylib
anki_audio/libs/libharfbuzz.0.dylib
anki_audio/libs/libhogweed.6.4.dylib
anki_audio/libs/libidn2.0.dylib
anki_audio/libs/libintl.8.dylib
anki_audio/libs/libjpeg.9.dylib
anki_audio/libs/libjxl.0.6.1.dylib
anki_audio/libs/liblcms2.2.dylib
anki_audio/libs/liblept.5.dylib
anki_audio/libs/liblz4.1.9.3.dylib
anki_audio/libs/liblzma.5.dylib
anki_audio/libs/libmbedcrypto.3.0.0.dylib
anki_audio/libs/libmp3lame.0.dylib
anki_audio/libs/libnettle.8.4.dylib
anki_audio/libs/libogg.0.dylib
anki_audio/libs/libopencore-amrnb.0.dylib
anki_audio/libs/libopencore-amrwb.0.dylib
anki_audio/libs/libopenjp2.2.4.0.dylib
anki_audio/libs/libopus.0.dylib
anki_audio/libs/libp11-kit.0.dylib
anki_audio/libs/libpcre.1.dylib
anki_audio/libs/libpng16.16.dylib
anki_audio/libs/libpostproc.55.9.100.dylib
anki_audio/libs/librav1e.0.5.0.dylib
anki_audio/libs/librist.4.dylib
anki_audio-0.1.0.dist-info/METADATA
anki_audio-0.1.0.dist-info/WHEEL
anki_audio-0.1.0.dist-info/RECORD
