Metadata-Version: 2.4
Name: anki-audio
Version: 0.1.0
Summary: Audio binaries (mpv, lame) for Anki
Project-URL: Homepage, https://github.com/ankitects/anki-bundle-extras
Author: Anki Team
License: GPL-2.0-or-later
Requires-Python: >=3.9
